dinotool/__init__.py
dinotool/__main__.py
dinotool/cli.py
dinotool/data.py
dinotool/model.py
dinotool/utils.py
dinotool-0.3.0.dist-info/METADATA
dinotool-0.3.0.dist-info/WHEEL
dinotool-0.3.0.dist-info/entry_points.txt
dinotool-0.3.0.dist-info/licenses/LICENSE
dinotool-0.3.0.dist-info/RECORD
