Metadata-Version: 2.4
Name: dinotool
Version: 0.3.0
Summary: Command-line tool for extracting DINO, CLIP and SigLIP features from images and videos
Project-URL: Homepage, https://github.com/mikkoim/dinotool
Project-URL: Issues, https://github.com/mikkoim/dinotool/issues
Author-email: Mikko Impiö <mikko.impio@gmail.com>
License: Apache License (2.0)
License-File: LICENSE
Keywords: computer vision,deep learning,dino,feature extraction,image processing,machine learning,video processing
Classifier: License :: OSI Approved :: Apache Software License
Classifier: Operating System :: OS Independent
Classifier: Programming Language :: Python :: 3.11
Classifier: Programming Language :: Python :: 3.12
Classifier: Programming Language :: Python :: 3.13
Requires-Python: >=3.11
Requires-Dist: accelerate>=1.10.0
Requires-Dist: einops>=0.8.1
Requires-Dist: h5py>=3.13.0
Requires-Dist: numpy>=2.0.0
Requires-Dist: open-clip-torch>=2.32.0
Requires-Dist: opencv-python>=4.11.0.86
Requires-Dist: pillow>=11.1.0
Requires-Dist: pyarrow>=19.0.1
Requires-Dist: scikit-learn>=1.6.1
Requires-Dist: torch>=2.6.0
Requires-Dist: torchvision>=0.21.0
Requires-Dist: tqdm>=4.67.1
Requires-Dist: transformers>=4.56.2
Requires-Dist: xarray>=2025.3.1
Requires-Dist: xformers>=0.0.29.post3; sys_platform == 'linux'
Requires-Dist: zarr>=3.0.6
